LICENSE
MANIFEST.in
README.rst
setup.cfg
setup.py
docs/CHANGELOG.rst
docs/Makefile
docs/conf.py
docs/index.rst
docs/tests.rst
docs/api/apache.rst
docs/api/arch.rst
docs/api/cron.rst
docs/api/deb.rst
docs/api/disk.rst
docs/api/files.rst
docs/api/git.rst
docs/api/group.rst
docs/api/gvm.rst
docs/api/index.rst
docs/api/mercurial.rst
docs/api/mysql.rst
docs/api/network.rst
docs/api/nginx.rst
docs/api/nodejs.rst
docs/api/openvz.rst
docs/api/opkg.rst
docs/api/oracle_jdk.rst
docs/api/pkg.rst
docs/api/portage.rst
docs/api/postgres.rst
docs/api/python.rst
docs/api/python_setuptools.rst
docs/api/rpm.rst
docs/api/service.rst
docs/api/shorewall.rst
docs/api/ssh.rst
docs/api/supervisor.rst
docs/api/system.rst
docs/api/systemd.rst
docs/api/tomcat.rst
docs/api/user.rst
docs/api/utils.rst
docs/api/vagrant.rst
docs/api/require/apache.rst
docs/api/require/arch.rst
docs/api/require/curl.rst
docs/api/require/deb.rst
docs/api/require/files.rst
docs/api/require/git.rst
docs/api/require/groups.rst
docs/api/require/index.rst
docs/api/require/mercurial.rst
docs/api/require/mysql.rst
docs/api/require/nginx.rst
docs/api/require/nodejs.rst
docs/api/require/openvz.rst
docs/api/require/opkg.rst
docs/api/require/oracle_jdk.rst
docs/api/require/pkg.rst
docs/api/require/portage.rst
docs/api/require/postfix.rst
docs/api/require/postgres.rst
docs/api/require/python.rst
docs/api/require/redis.rst
docs/api/require/rpm.rst
docs/api/require/service.rst
docs/api/require/shorewall.rst
docs/api/require/supervisor.rst
docs/api/require/system.rst
docs/api/require/tomcat.rst
docs/api/require/users.rst
fabtools/__init__.py
fabtools/apache.py
fabtools/arch.py
fabtools/conda.py
fabtools/cron.py
fabtools/deb.py
fabtools/disk.py
fabtools/files.py
fabtools/git.py
fabtools/group.py
fabtools/gvm.py
fabtools/mercurial.py
fabtools/mysql.py
fabtools/network.py
fabtools/nginx.py
fabtools/nodejs.py
fabtools/opkg.py
fabtools/oracle_jdk.py
fabtools/pkg.py
fabtools/portage.py
fabtools/postgres.py
fabtools/python.py
fabtools.egg-info/PKG-INFO
fabtools.egg-info/SOURCES.txt
fabtools.egg-info/dependency_links.txt
fabtools.egg-info/not-zip-safe
fabtools.egg-info/requires.txt
fabtools.egg-info/top_level.txt
